[
  {
    "site": "pocerady",
    "site_type": "emitter",
    "sc_ratio": null,
    "precision_10km": 0.0127,
    "total_events": 785,
    "slope": -0.012822,
    "intercept": -3.966022,
    "r2": 0.535,
    "gradient_score": 12.822,
    "near_far_ratio": 2.223,
    "n_rings": 10
  },
  {
    "site": "brindisi",
    "site_type": "emitter",
    "sc_ratio": null,
    "precision_10km": 0.0365,
    "total_events": 2029,
    "slope": -0.012492,
    "intercept": -3.308995,
    "r2": 0.801,
    "gradient_score": 12.492,
    "near_far_ratio": 1.974,
    "n_rings": 10
  },
  {
    "site": "ctrl_nl_flevoland",
    "site_type": "control",
    "sc_ratio": null,
    "precision_10km": 0.5,
    "total_events": 4,
    "slope": -0.011405,
    "intercept": -4.731397,
    "r2": 0.872,
    "gradient_score": 11.405,
    "near_far_ratio": 1.444,
    "n_rings": 10
  },
  {
    "site": "irsching",
    "site_type": "emitter_miss",
    "sc_ratio": null,
    "precision_10km": 0.0,
    "total_events": 38,
    "slope": -0.010186,
    "intercept": -5.062458,
    "r2": 0.829,
    "gradient_score": 10.186,
    "near_far_ratio": 1.54,
    "n_rings": 10
  },
  {
    "site": "belchatow",
    "site_type": "emitter",
    "sc_ratio": null,
    "precision_10km": 0.0505,
    "total_events": 99,
    "slope": -0.00602,
    "intercept": -4.652351,
    "r2": 0.771,
    "gradient_score": 6.02,
    "near_far_ratio": 1.405,
    "n_rings": 10
  },
  {
    "site": "ctrl_fr_berry",
    "site_type": "control",
    "sc_ratio": null,
    "precision_10km": 0.0465,
    "total_events": 688,
    "slope": -0.006014,
    "intercept": -4.288764,
    "r2": 0.453,
    "gradient_score": 6.014,
    "near_far_ratio": 1.519,
    "n_rings": 10
  },
  {
    "site": "maasvlakte",
    "site_type": "emitter",
    "sc_ratio": null,
    "precision_10km": 0.8333,
    "total_events": 6,
    "slope": -0.005622,
    "intercept": -4.612908,
    "r2": 0.603,
    "gradient_score": 5.622,
    "near_far_ratio": 1.35,
    "n_rings": 10
  },
  {
    "site": "dunkerque",
    "site_type": "emitter",
    "sc_ratio": null,
    "precision_10km": 0.0769,
    "total_events": 13,
    "slope": -0.005423,
    "intercept": -4.804954,
    "r2": 0.589,
    "gradient_score": 5.423,
    "near_far_ratio": 1.371,
    "n_rings": 10
  },
  {
    "site": "larobla",
    "site_type": "emitter",
    "sc_ratio": null,
    "precision_10km": 0.0285,
    "total_events": 2140,
    "slope": -0.004155,
    "intercept": -3.918512,
    "r2": 0.191,
    "gradient_score": 4.155,
    "near_far_ratio": 1.169,
    "n_rings": 10
  },
  {
    "site": "ctrl_it_basilicata",
    "site_type": "control",
    "sc_ratio": null,
    "precision_10km": 0.0,
    "total_events": 273,
    "slope": -0.003264,
    "intercept": -4.667094,
    "r2": 0.31,
    "gradient_score": 3.264,
    "near_far_ratio": 1.104,
    "n_rings": 7
  },
  {
    "site": "philippsburg",
    "site_type": "emitter_closed",
    "sc_ratio": null,
    "precision_10km": 0.0,
    "total_events": 32,
    "slope": -0.001155,
    "intercept": -5.22634,
    "r2": 0.245,
    "gradient_score": 1.155,
    "near_far_ratio": 1.05,
    "n_rings": 10
  },
  {
    "site": "ctrl_de_swabian_alb",
    "site_type": "control",
    "sc_ratio": null,
    "precision_10km": 0.0213,
    "total_events": 47,
    "slope": 0.00087,
    "intercept": -5.401907,
    "r2": 0.177,
    "gradient_score": -0.87,
    "near_far_ratio": 0.975,
    "n_rings": 10
  },
  {
    "site": "ctrl_dk_jutland",
    "site_type": "control",
    "sc_ratio": null,
    "precision_10km": 0.0163,
    "total_events": 123,
    "slope": 0.001058,
    "intercept": -5.326551,
    "r2": 0.116,
    "gradient_score": -1.058,
    "near_far_ratio": 0.875,
    "n_rings": 10
  },
  {
    "site": "cordemais",
    "site_type": "emitter_miss",
    "sc_ratio": null,
    "precision_10km": 0.0,
    "total_events": 48,
    "slope": 0.001999,
    "intercept": -5.572973,
    "r2": 0.159,
    "gradient_score": -1.999,
    "near_far_ratio": 0.88,
    "n_rings": 8
  },
  {
    "site": "ctrl_pl_mazovia",
    "site_type": "control",
    "sc_ratio": null,
    "precision_10km": 0.0,
    "total_events": 205,
    "slope": 0.006382,
    "intercept": -4.699685,
    "r2": 0.389,
    "gradient_score": -6.382,
    "near_far_ratio": 0.903,
    "n_rings": 8
  },
  {
    "site": "ctrl_es_castilla",
    "site_type": "control",
    "sc_ratio": null,
    "precision_10km": 0.0004,
    "total_events": 5656,
    "slope": 0.006552,
    "intercept": -3.697322,
    "r2": 0.841,
    "gradient_score": -6.552,
    "near_far_ratio": 0.732,
    "n_rings": 9
  },
  {
    "site": "avedore",
    "site_type": "emitter_miss",
    "sc_ratio": null,
    "precision_10km": 0.0,
    "total_events": 259,
    "slope": 0.008224,
    "intercept": -5.099853,
    "r2": 0.305,
    "gradient_score": -8.224,
    "near_far_ratio": 0.514,
    "n_rings": 9
  },
  {
    "site": "ctrl_cz_bohemia_east",
    "site_type": "control",
    "sc_ratio": null,
    "precision_10km": 0.0,
    "total_events": 307,
    "slope": 0.013775,
    "intercept": -5.679266,
    "r2": 0.823,
    "gradient_score": -13.775,
    "near_far_ratio": 0.633,
    "n_rings": 8
  },
  {
    "site": "groningen",
    "site_type": "emitter",
    "sc_ratio": null,
    "precision_10km": 0.3333,
    "total_events": 24,
    "slope": 0.015895,
    "intercept": -5.531534,
    "r2": 0.812,
    "gradient_score": -15.895,
    "near_far_ratio": 0.577,
    "n_rings": 10
  }
]